pulumi_koyeb/__init__.py
pulumi_koyeb/_inputs.py
pulumi_koyeb/_utilities.py
pulumi_koyeb/app.py
pulumi_koyeb/domain.py
pulumi_koyeb/get_app.py
pulumi_koyeb/get_domain.py
pulumi_koyeb/get_secret.py
pulumi_koyeb/get_service.py
pulumi_koyeb/outputs.py
pulumi_koyeb/provider.py
pulumi_koyeb/pulumi-plugin.json
pulumi_koyeb/py.typed
pulumi_koyeb/secret.py
pulumi_koyeb/service.py
pulumi_koyeb/volume.py
pulumi_koyeb-0.1.11.dist-info/METADATA
pulumi_koyeb-0.1.11.dist-info/WHEEL
pulumi_koyeb-0.1.11.dist-info/top_level.txt
pulumi_koyeb-0.1.11.dist-info/RECORD
