Metadata-Version: 2.1
Name: pulumi_koyeb
Version: 0.1.11
Summary: A Pulumi package for creating and managing koyeb cloud resources.
License: Apache-2.0
Project-URL: Homepage, https://www.koyeb.com
Project-URL: Repository, https://github.com/koyeb/pulumi-koyeb
Keywords: koyeb,category/cloud
Requires-Python: >=3.8
Requires-Dist: parver>=0.2.1
Requires-Dist: pulumi<4.0.0,>=3.136.0
Requires-Dist: semver>=2.8.1
Requires-Dist: typing-extensions>=4.11; python_version < "3.11"
